aws_adfs/__init__.py
aws_adfs/_azure_cloud_mfa_authenticator.py
aws_adfs/_azure_mfa_authenticator.py
aws_adfs/_duo_authenticator.py
aws_adfs/_duo_universal_prompt_authenticator.py
aws_adfs/_rsa_authenticator.py
aws_adfs/_safenet_mfa.py
aws_adfs/_silverfort_authenticator.py
aws_adfs/_symantec_vip_access.py
aws_adfs/account_aliases_fetcher.py
aws_adfs/authenticator.py
aws_adfs/commands.py
aws_adfs/consts.py
aws_adfs/helpers.py
aws_adfs/html_roles_fetcher.py
aws_adfs/list_profiles.py
aws_adfs/login.py
aws_adfs/prepare.py
aws_adfs/reset.py
aws_adfs/role_chooser.py
aws_adfs/roles_assertion_extractor.py
aws_adfs/run_command.py
aws_adfs-2.12.1.dist-info/entry_points.txt
aws_adfs-2.12.1.dist-info/LICENSE
aws_adfs-2.12.1.dist-info/WHEEL
aws_adfs-2.12.1.dist-info/METADATA
aws_adfs-2.12.1.dist-info/RECORD
